d3vis_ipynb/__init__.py
d3vis_ipynb/_version.py
d3vis_ipynb/base_widget.py
d3vis_ipynb/custom.py
d3vis_ipynb/graphs.py
d3vis_ipynb/layouts.py
d3vis_ipynb/medias.py
d3vis_ipynb/widgets.py
d3vis_ipynb/labextension/package.json
d3vis_ipynb/labextension/static/493.dd901d242b4fdb225a45.js
d3vis_ipynb/labextension/static/561.0be35d7b6ab2355caa6b.js
d3vis_ipynb/labextension/static/693.d4b3da40596a8427eec6.js
d3vis_ipynb/labextension/static/920.94de5499a7505c5450e7.js
d3vis_ipynb/labextension/static/920.94de5499a7505c5450e7.js.LICENSE.txt
d3vis_ipynb/labextension/static/remoteEntry.c19b1efb0a67415ce161.js
d3vis_ipynb/labextension/static/style.js
d3vis_ipynb/labextension/static/third-party-licenses.json
d3vis_ipynb/nbextension/index.js
d3vis_ipynb/nbextension/index.js.LICENSE.txt
d3vis_ipynb-0.4.2.data/data/share/jupyter/labextensions/d3vis_ipynb/package.json
d3vis_ipynb-0.4.2.data/data/share/jupyter/labextensions/d3vis_ipynb/static/493.dd901d242b4fdb225a45.js
d3vis_ipynb-0.4.2.data/data/share/jupyter/labextensions/d3vis_ipynb/static/561.0be35d7b6ab2355caa6b.js
d3vis_ipynb-0.4.2.data/data/share/jupyter/labextensions/d3vis_ipynb/static/693.d4b3da40596a8427eec6.js
d3vis_ipynb-0.4.2.data/data/share/jupyter/labextensions/d3vis_ipynb/static/920.94de5499a7505c5450e7.js
d3vis_ipynb-0.4.2.data/data/share/jupyter/labextensions/d3vis_ipynb/static/920.94de5499a7505c5450e7.js.LICENSE.txt
d3vis_ipynb-0.4.2.data/data/share/jupyter/labextensions/d3vis_ipynb/static/remoteEntry.c19b1efb0a67415ce161.js
d3vis_ipynb-0.4.2.data/data/share/jupyter/labextensions/d3vis_ipynb/static/style.js
d3vis_ipynb-0.4.2.data/data/share/jupyter/labextensions/d3vis_ipynb/static/third-party-licenses.json
d3vis_ipynb-0.4.2.data/data/share/jupyter/nbextensions/d3vis_ipynb/index.js
d3vis_ipynb-0.4.2.data/data/share/jupyter/nbextensions/d3vis_ipynb/index.js.LICENSE.txt
d3vis_ipynb-0.4.2.data/data/share/jupyter/labextensions/d3vis_ipynb/install.json
d3vis_ipynb-0.4.2.dist-info/METADATA
d3vis_ipynb-0.4.2.dist-info/WHEEL
d3vis_ipynb-0.4.2.dist-info/licenses/LICENSE.txt
d3vis_ipynb-0.4.2.dist-info/RECORD
